pomegranate_mathematica/__init__.py
pomegranate_mathematica-0.1.dist-info/LICENSE
pomegranate_mathematica-0.1.dist-info/METADATA
pomegranate_mathematica-0.1.dist-info/WHEEL
pomegranate_mathematica-0.1.dist-info/top_level.txt
pomegranate_mathematica-0.1.dist-info/RECORD
