Metadata-Version: 2.1
Name: pomegranate-mathematica
Version: 0.1
Summary: Wolfram Mathematica distributions parser for pomegranate
Home-page: https://github.com/d-lowl/pomegranate-mathematica
Author: D. Lowl
Author-email: dlowl@sihvi.com
License: MIT
Platform: UNKNOWN
Requires-Dist: pomegranate (==0.11)
Requires-Dist: lark-parser
